pydantic_strict_partial/__init__.py
pydantic_strict_partial/py.typed
pydantic_strict_partial-0.6.2.dist-info/LICENSE
pydantic_strict_partial-0.6.2.dist-info/METADATA
pydantic_strict_partial-0.6.2.dist-info/WHEEL
pydantic_strict_partial-0.6.2.dist-info/RECORD
