Metadata-Version: 2.3
Name: pydantic-strict-partial
Version: 0.6.2
Summary: Makes partial Pydantic models without making fields nullable.
License: MIT
Keywords: pydantic,partial,fastapi
Author: Adrian Dankiv
Author-email: adr-007@ukr.net
Requires-Python: >=3.10,<4.0
Classifier: Development Status :: 4 - Beta
Classifier: Framework :: Pydantic :: 2
Classifier: Intended Audience :: Developers
Classifier: License :: OSI Approved :: MIT License
Classifier: Programming Language :: Python :: 3
Classifier: Programming Language :: Python :: 3.10
Classifier: Programming Language :: Python :: 3.11
Classifier: Programming Language :: Python :: 3.12
Classifier: Programming Language :: Python :: 3.13
Requires-Dist: pydantic (>=2.1,<3.0)
Project-URL: Homepage, https://github.com/ADR-007/pydantic-strict-partial
